chiron_bot/__init__.py
chiron_bot/chiron_hangouts.py
chiron_bot/chiron_zephyr.py
chiron_bot/chiron_zulip.py
chiron_bot/engine.py
chiron_bot/fetchers.py
chiron_bot/main.py
chiron_bot/test_doctest.py
chiron_bot/test_engine.py
chiron_bot_adehnert-0.9.1.dist-info/LICENSE
chiron_bot_adehnert-0.9.1.dist-info/METADATA
chiron_bot_adehnert-0.9.1.dist-info/WHEEL
chiron_bot_adehnert-0.9.1.dist-info/entry_points.txt
chiron_bot_adehnert-0.9.1.dist-info/top_level.txt
chiron_bot_adehnert-0.9.1.dist-info/RECORD
