Metadata-Version: 2.1
Name: chiron-bot-adehnert
Version: 0.9.1
Summary: Chat bot that can look up ticket numbers on bugtrackers and return their names
Home-page: https://github.com/sipb/chiron
Author: Alex Dehnert and MIT SIPB
Author-email: chiron@mit.edu
License: UNKNOWN
Platform: UNKNOWN
Classifier: Development Status :: 5 - Production/Stable
Classifier: License :: OSI Approved :: MIT License
Classifier: Environment :: No Input/Output (Daemon)
Classifier: Programming Language :: Python :: 2
Classifier: Programming Language :: Python :: 3
Classifier: Topic :: Communications :: Chat
Requires-Python: >=3.6
Requires-Dist: lxml
Requires-Dist: requests[security]
Requires-Dist: backports.csv ; python_version < "3"
Provides-Extra: hangouts
Requires-Dist: hangups ; extra == 'hangouts'
Provides-Extra: test
Requires-Dist: unittest-xml-reporting ; extra == 'test'
Provides-Extra: zulip
Requires-Dist: zulip ; extra == 'zulip'
